post_processing/__init__.py
post_processing/post_processor.py
post_processing_library_tushar-0.1.dist-info/METADATA
post_processing_library_tushar-0.1.dist-info/WHEEL
post_processing_library_tushar-0.1.dist-info/top_level.txt
post_processing_library_tushar-0.1.dist-info/RECORD
