Metadata-Version: 2.1
Name: post-processing-library-tushar
Version: 0.1
Summary: A library for post-processing entities
Author: Tushar
Author-email: mahuritushar@gmail.com
Requires-Dist: fuzzywuzzy
